Workbook

Sheet Sales_Data
A1: Order_ID | B1: Order_Date | C1: Customer_ID | D1: Product | E1: Category | F1: Region | G1: Quantity | H1: Unit_Price | I1: Discount | J1: Sales | K1: Cost | L1: Profit | M1: Profit Margin | N1: Month | O1: Year | P1: Discount Amount
A2: ORD003078 | B2: 45292 | C2: CUST01923 | D2: Football | E2: Sports | F2: Central | G2: 3 | H2: 1385 | I2: 0.1 | J2: 3739.5 | K2: 2695.46 | L2: 1044.04 | M2: =L2/J2 -> 0.27919241 | N2: =TEXT(B2,"mm") -> 01 | O2: =YEAR(B2) -> 2024 | P2: =G2*H2*I2 -> 415.5
A3: ORD002878 | B3: 45292 | C3: CUST02310 | D3: Keyboard | E3: Electronics | F3: North | G3: 1 | H3: 1593 | I3: 0.05 | J3: 1513.35 | K3: 1026.78 | L3: 486.57 | M3: =L3/J3 -> 0.32151849 | N3: =TEXT(B3,"mm") -> 01 | O3: =YEAR(B3) -> 2024 | P3: =G3*H3*I3 -> 79.65
A4: ORD007673 | B4: 45292 | C4: CUST01666 | D4: Headphones | E4: Electronics | F4: East | G4: 1 | H4: 4985 | I4: 0 | J4: 4985 | K4: 3745.54 | L4: 1239.46 | M4: =L4/J4 -> 0.24863791 | N4: =TEXT(B4,"mm") -> 01 | O4: =YEAR(B4) -> 2024 | P4: =G4*H4*I4 -> 0
A5: ORD007588 | B5: 45292 | C5: CUST01931 | D5: Laptop | E5: Electronics | F5: Central | G5: 1 | H5: 79069 | I5: 0 | J5: 79069 | K5: 52498.06 | L5: 26570.94 | M5: =L5/J5 -> 0.3360475 | N5: =TEXT(B5,"mm") -> 01 | O5: =YEAR(B5) -> 2024 | P5: =G5*H5*I5 -> 0
A6: ORD008762 | B6: 45292 | C6: CUST00316 | D6: Monitor | E6: Electronics | F6: South | G6: 1 | H6: 22420 | I6: 0.05 | J6: 21299 | K6: 16819.05 | L6: 4479.95 | M6: =L6/J6 -> 0.21033617 | N6: =TEXT(B6,"mm") -> 01 | O6: =YEAR(B6) -> 2024 | P6: =G6*H6*I6 -> 1121
A7: ORD001390 | B7: 45292 | C7: CUST01870 | D7: Bookshelf | E7: Furniture | F7: North | G7: 4 | H7: 4284 | I7: 0.05 | J7: 16279.2 | K7: 13729.27 | L7: 2549.93 | M7: =L7/J7 -> 0.1566373 | N7: =TEXT(B7,"mm") -> 01 | O7: =YEAR(B7) -> 2024 | P7: =G7*H7*I7 -> 856.8
A8: ORD001962 | B8: 45292 | C8: CUST00956 | D8: Laptop | E8: Electronics | F8: East | G8: 4 | H8: 76226 | I8: 0.1 | J8: 274413.6 | K8: 245990.11 | L8: 28423.49 | M8: =L8/J8 -> 0.10357901 | N8: =TEXT(B8,"mm") -> 01 | O8: =YEAR(B8) -> 2024 | P8: =G8*H8*I8 -> 30490.4
A9: ORD000520 | B9: 45292 | C9: CUST01807 | D9: Water Bottle | E9: Accessories | F9: West | G9: 3 | H9: 1142 | I9: 0.05 | J9: 3254.7 | K9: 2103.97 | L9: 1150.73 | M9: =L9/J9 -> 0.35355947 | N9: =TEXT(B9,"mm") -> 01 | O9: =YEAR(B9) -> 2024 | P9: =G9*H9*I9 -> 171.3
A10: ORD008236 | B10: 45292 | C10: CUST00597 | D10: Football | E10: Sports | F10: Central | G10: 3 | H10: 628 | I10: 0.1 | J10: 1695.6 | K10: 1117.02 | L10: 578.58 | M10: =L10/J10 -> 0.34122435 | N10: =TEXT(B10,"mm") -> 01 | O10: =YEAR(B10) -> 2024 | P10: =G10*H10*I10 -> 188.4
A11: ORD000308 | B11: 45292 | C11: CUST00442 | D11: Notebook | E11: Stationery | F11: North | G11: 3 | H11: 166 | I11: 0 | J11: 498 | K11: 319.67 | L11: 178.33 | M11: =L11/J11 -> 0.35809237 | N11: =TEXT(B11,"mm") -> 01 | O11: =YEAR(B11) -> 2024 | P11: =G11*H11*I11 -> 0
A12: ORD006871 | B12: 45292 | C12: CUST01972 | D12: Backpack | E12: Accessories | F12: Central | G12: 2 | H12: 2912 | I12: 0.1 | J12: 5241.6 | K12: 4489.23 | L12: 752.37 | M12: =L12/J12 -> 0.14353823 | N12: =TEXT(B12,"mm") -> 01 | O12: =YEAR(B12) -> 2024 | P12: =G12*H12*I12 -> 582.4
A13: ORD006781 | B13: 45292 | C13: CUST01992 | D13: Laptop | E13: Electronics | F13: Central | G13: 1 | H13: 78731 | I13: 0 | J13: 78731 | K13: 55549.71 | L13: 23181.29 | M13: =L13/J13 -> 0.29443663 | N13: =TEXT(B13,"mm") -> 01 | O13: =YEAR(B13) -> 2024 | P13: =G13*H13*I13 -> 0
... A10001: ORD002325 | B10001: 46022 | C10001: CUST00777 | D10001: Pen Set | E10001: Stationery | F10001: Central | G10001: 2 | H10001: 50 | I10001: 0.1 | J10001: 90 | K10001: 62.85 | L10001: 27.15 | M10001: =L10001/J10001 -> 0.30166667 | N10001: =TEXT(B10001,"mm") -> 12 | O10001: =YEAR(B10001) -> 2025 | P10001: =G10001*H10001*I10001 -> 10

Sheet pivot table
A3: Category | B3: Sum of Sales | C3: Sum of Profit | F3: Region | G3: Sum of Sales | H3: Sum of Profit | L3: Product | M3: Sum of Profit | N3: Sum of Sales | O3: Sum of Quantity | T3: Month And Year | U3: Sum of Sales | V3: Sum of Profit | Z3: Discount | AA3: Sum of Profit
A4: Accessories | B4: 2737156.9 | C4: 724001.48 | F4: Central | G4: 43137822 | H4: 11181884 | L4: Laptop | M4: 27990988 | N4: 1.0818069e+08 | O4: 1718 | T4: 2024 | U4: 1.1965714e+08 | V4: 31681296 | Z4: 0 | AA4: 19610669
A5: Electronics | B5: 1.8528601e+08 | C5: 48182335 | F5: East | G5: 46801838 | H5: 12299878 | L5: Smartphone | M5: 13581662 | N5: 51327610 | O5: 2108 | T5: Jan | U5: 10438843 | V5: 2770467 | Z5: 0.05 | AA5: 19716430
A6: Furniture | B6: 34717929 | C6: 9250131 | F6: North | G6: 44703158 | H6: 11815871 | L6: Monitor | M6: 4920317.7 | N6: 19287146 | O6: 1191 | T6: Feb | U6: 9124147.9 | V6: 2232390 | Z6: 0.1 | AA6: 14041268
A7: Sports | B7: 5333392.6 | C7: 1391492 | F7: South | G7: 44714794 | H7: 11731118 | L7: Desk | M7: 4189924.2 | N7: 15548411 | O7: 1167 | T7: Mar | U7: 9337803.4 | V7: 2475347.3 | Z7: 0.15 | AA7: 4735545.6
A8: Stationery | B8: 378573.4 | C8: 100488.73 | F8: West | G8: 49095449 | H8: 12619698 | L8: Office Chair | M8: 3744451.2 | N8: 14108542 | O8: 1328 | T8: Apr | U8: 8299597.5 | V8: 2225195.4 | Z8: 0.2 | AA8: 1544535.5
A9: Grand Total | B9: 2.2845306e+08 | C9: 59648448 | F9: Grand Total | G9: 2.2845306e+08 | H9: 59648448 | L9: Bookshelf | M9: 1315755.7 | N9: 5060976.3 | O9: 837 | T9: May | U9: 9738331.4 | V9: 2706402.4 | Z9: Grand Total | AA9: 59648448
L10: Headphones | M10: 1157144.5 | N10: 4468717.8 | O10: 1534 | T10: Jun | U10: 9480057.6 | V10: 2618480.8
L11: Running Shoes | M11: 963835.3 | N11: 3675636.4 | O11: 1029 | T11: Jul | U11: 12155932 | V11: 3187032.9
L12: Backpack | M12: 543763.58 | N12: 2057567.1 | O12: 1164 | T12: Aug | U12: 11322057 | V12: 3007599.6
L13: Keyboard | M13: 532222.73 | N13: 2021840.2 | O13: 1179 | T13: Sep | U13: 11471004 | V13: 2990061.2
L14: Grand Total | M14: 58940065 | N14: 2.2573714e+08 | O14: 13255 | T14: Oct | U14: 9410664.9 | V14: 2521115.7
T15: Nov | U15: 9636048.5 | V15: 2430288.7
T16: Dec | U16: 9242649.5 | V16: 2516914.8
T17: 2025 | U17: 1.0879592e+08 | V17: 27967153
T18: Jan | U18: 10567129 | V18: 2728460.1
T19: Feb | U19: 7328700.6 | V19: 1971518.1
T20: Mar | U20: 9023871 | V20: 2222844.6
T21: Apr | U21: 8436898.1 | V21: 2157771
T22: May | U22: 10036595 | V22: 2634196.1
T23: Jun | U23: 9310825.1 | V23: 2369872.6
T24: Jul | U24: 8381049.6 | V24: 2154885.6
T25: Aug | U25: 8613199 | V25: 2166282.8
T26: Sep | U26: 7731864.8 | V26: 2087456
... T30: Grand Total | U30: 2.2845306e+08 | V30: 59648448

Sheet excel_analysis
N2: E-COMMERCE SALES & PROFIT ANALYSIS
I5: Total Sales | K5: Total Cost | N5: Total Profit | Q5: Total Orders | T5: Average Order Value | W5: Profit Margin
I6: =SUM(Sales_Data!J:J) -> 2.2845306e+08 | K6: =SUM(Sales_Data!K:K) -> 1.6880461e+08 | N6: =SUM(Sales_Data!L:L) -> 59648448 | Q6: =COUNTA(Sales_Data!A:A)-1 -> 10000 | T6: =SUM(Sales_Data!J:J)/(COUNTA(Sales_Data!A:A)-1) -> 22845.306 | W6: =SUM(Sales_Data!L:L)/SUM(Sales_Data!J:J) -> 0.26109717
D87: KEY BUSINESS INSIGHTS
B91: Category: Electronics generated approximately 81% of total sales and contributed ₹48.18M in profit.
B93: • Region: North was the most profitable region, generating approximately ₹18.92M in profit.
B95: • Product: Laptops were the most profitable product, generating approximately ₹27.99M in profit.
B97: • Monthly Trend: November 2025 recorded the highest monthly sales at approximately ₹12.47M.
B99: • Discount Impact: Profit remained relatively stable at 0–5% discounts but declined sharply at discounts above 5%.

Sheet  charts_data
E1: Product | F1: Sum of Profit | J1: Category | K1: Sum of Sales
A2: Region | B2: Sum of Profit | E2: Laptop | F2: 27990988 | J2: Electronics | K2: 1.8528601e+08
A3: West | B3: 12619698 | E3: Smartphone | F3: 13581662 | J3: Furniture | K3: 34717929
A4: East | B4: 12299878 | E4: Monitor | F4: 4920317.7 | J4: Sports | K4: 5333392.6
A5: North | B5: 11815871 | E5: Desk | F5: 4189924.2 | J5: Accessories | K5: 2737156.9
A6: South | B6: 11731118 | E6: Office Chair | F6: 3744451.2 | J6: Stationery | K6: 378573.4
A7: Central | B7: 11181884 | E7: Bookshelf | F7: 1315755.7
E8: Headphones | F8: 1157144.5
E9: Running Shoes | F9: 963835.3
E10: Backpack | F10: 543763.58
E11: Keyboard | F11: 532222.73
E12: Grand Total | F12: 58940065
